[
  {
    "agent_name":"resume_agent",
    "task":"extract_content",
    "id":1,
    "input":"John Smith\nSenior Software Engineer\n\nEmail: john.smith@example.com\nGitHub: github.com\/johnsmith\nLinkedIn: linkedin.com\/in\/johnsmith\n\nProfessional Summary:\nExperienced software engineer with over 8 years of expertise in building scalable web applications using JavaScript, Python, and cloud technologies. Passionate about clean code and user-centric design.\n\nExperience:\nTechCorp Inc. | Jan 2020 - Present\nSenior Software Engineer\n- Led development of the company's flagship product, increasing performance by 40%\n- Mentored junior developers and implemented code review processes\n- Architected microservices infrastructure using AWS and Kubernetes\n\nInnovate Solutions | Mar 2017 - Dec 2019\nSoftware Developer\n- Developed RESTful APIs serving over 1M requests daily\n- Collaborated with UX team to implement responsive frontend using React\n- Improved CI\/CD pipeline, reducing deployment time by 65%\n\nCodeWorks | Jun 2015 - Feb 2017\nJunior Developer\n- Built internal tools for data processing and analysis\n- Maintained legacy PHP applications and migrated components to Python\n- Participated in Agile development processes",
    "output":"{\n  \"name\": \"John Smith\",\n  \"title\": \"Senior Software Engineer\",\n  \"email\": \"john.smith@example.com\",\n  \"github\": \"github.com\/johnsmith\",\n  \"linkedin\": \"linkedin.com\/in\/johnsmith\",\n  \"summary\": \"Experienced software engineer with over 8 years of expertise in building scalable web applications using JavaScript, Python, and cloud technologies. Passionate about clean code and user-centric design.\",\n  \"experience\": [\n    {\n      \"company\": \"TechCorp Inc.\",\n      \"date\": \"Jan 2020 - Present\",\n      \"title\": \"Senior Software Engineer\",\n      \"description\": \"\u2022 Led development of the company's flagship product, increasing performance by 40%\\n\u2022 Mentored junior developers and implemented code review processes\\n\u2022 Architected microservices infrastructure using AWS and Kubernetes\"\n    },\n    {\n      \"company\": \"Innovate Solutions\",\n      \"date\": \"Mar 2017 - Dec 2019\",\n      \"title\": \"Software Developer\",\n      \"description\": \"\u2022 Developed RESTful APIs serving over 1M requests daily\\n\u2022 Collaborated with UX team to implement responsive frontend using React\\n\u2022 Improved CI\/CD pipeline, reducing deployment time by 65%\"\n    },\n    {\n      \"company\": \"CodeWorks\",\n      \"date\": \"Jun 2015 - Feb 2017\",\n      \"title\": \"Junior Developer\",\n      \"description\": \"\u2022 Built internal tools for data processing and analysis\\n\u2022 Maintained legacy PHP applications and migrated components to Python\\n\u2022 Participated in Agile development processes\"\n    }\n  ]\n}",
    "remarks":"standard resume format"
  },
  {
    "agent_name":"resume_agent",
    "task":"extract_content",
    "id":2,
    "input":"EMILY CHEN\nDATA SCIENTIST & MACHINE LEARNING ENGINEER\nemily.chen@datascience.io\n\nABOUT ME\n-------------------------------\nInnovative data scientist with a knack for turning complex datasets into actionable insights. \nSpecialized in natural language processing and predictive modeling with 5+ years of \nhands-on experience implementing ML solutions for Fortune 500 companies.\n\nPROFESSIONAL JOURNEY\n-------------------------------\nDATATECH INNOVATIONS\nChief Data Scientist | 2023-Present\n* Spearheaded development of NLP models that increased customer sentiment analysis accuracy by 35%\n* Managing team of 6 data scientists working on next-generation recommendation engines\n* Secured $1.2M in additional funding through successful POC development\n\nANALYTIX GROUP\nSenior Machine Learning Engineer | 2020-2022\n* Developed and deployed production ML models using TensorFlow and PyTorch\n* Created anomaly detection system resulting in $3M fraud prevention\n* Optimized data pipelines reducing processing time by 60%\n\nTECHSTART INC.\nData Scientist | 2018-2020\n* Built customer segmentation models increasing marketing campaign effectiveness by 28%\n* Implemented A\/B testing framework for feature evaluation\n* Collaborated with product team to integrate data-driven decision making processes",
    "output":"{\n  \"name\": \"Emily Chen\",\n  \"title\": \"Data Scientist & Machine Learning Engineer\",\n  \"email\": \"emily.chen@datascience.io\",\n  \"github\": null,\n  \"linkedin\": null,\n  \"summary\": \"Innovative data scientist with a knack for turning complex datasets into actionable insights. Specialized in natural language processing and predictive modeling with 5+ years of hands-on experience implementing ML solutions for Fortune 500 companies.\",\n  \"experience\": [\n    {\n      \"company\": \"Datatech Innovations\",\n      \"date\": \"2023-Present\",\n      \"title\": \"Chief Data Scientist\",\n      \"description\": \"* Spearheaded development of NLP models that increased customer sentiment analysis accuracy by 35%\\n* Managing team of 6 data scientists working on next-generation recommendation engines\\n* Secured $1.2M in additional funding through successful POC development\"\n    },\n    {\n      \"company\": \"Analytix Group\",\n      \"date\": \"2020-2022\",\n      \"title\": \"Senior Machine Learning Engineer\",\n      \"description\": \"* Developed and deployed production ML models using TensorFlow and PyTorch\\n* Created anomaly detection system resulting in $3M fraud prevention\\n* Optimized data pipelines reducing processing time by 60%\"\n    },\n    {\n      \"company\": \"Techstart Inc.\",\n      \"date\": \"2018-2020\",\n      \"title\": \"Data Scientist\",\n      \"description\": \"* Built customer segmentation models increasing marketing campaign effectiveness by 28%\\n* Implemented A\/B testing framework for feature evaluation\\n* Collaborated with product team to integrate data-driven decision making processes\"\n    }\n  ]\n}",
    "remarks":"creative format with missing fields"
  },
  {
    "agent_name":"resume_agent",
    "task":"extract_content",
    "id":3,
    "input":"=================================\nAlexander Washington\nProduct Design Leader\n=================================\nalex@designcraft.co | github.com\/awashington-design | linkedin.com\/in\/alexander-washington-design\n\nI transform complex problems into elegant, user-centered product experiences. With 12+ years navigating all aspects of product design, I blend strategic thinking with hands-on execution to drive business growth while advocating relentlessly for user needs.\n\nCAREER HIGHLIGHTS\n-------------------\n\n\u2726 DESIGN DIRECTOR \u2726\nFuture Interfaces\nSeptember 2021 - Current\n\nLeading design operations for AI-powered productivity tools with a team of 15 designers\n- Established design system reducing implementation time by 65%\n- Pioneered accessibility-first approach resulting in WCAG AA compliance\n- Secured $5M additional funding through successful design-led initiatives\n- Doubled user retention through redesign of core product experiences\n\n\u2726 SENIOR PRODUCT DESIGNER \u2726\nInnovateTech Solutions\nApril 2018 - August 2021\n\nHeaded design for flagship enterprise collaboration platform\n- Reimagined onboarding flow increasing activation rates by 47%\n- Conducted extensive user research across 5 countries and 200+ participants\n- Developed UX strategy aligned with business KPIs, contributing to 128% revenue growth\n- Mentored junior designers and established design critique processes\n\n\u2726 UX DESIGNER \u2726\nCraft Digital Agency\nMarch 2015 - March 2018\n\nLed design for high-profile client projects across fintech, healthcare and education sectors\n- Designed award-winning mobile banking application (UXDA Financial Design Award 2017)\n- Created user research frameworks adopted company-wide\n- Managed client relationships and presentation of design concepts to C-level stakeholders",
    "output":"{\n  \"name\": \"Alexander Washington\",\n  \"title\": \"Product Design Leader\",\n  \"email\": \"alex@designcraft.co\",\n  \"github\": \"github.com\/awashington-design\",\n  \"linkedin\": \"linkedin.com\/in\/alexander-washington-design\",\n  \"summary\": \"I transform complex problems into elegant, user-centered product experiences. With 12+ years navigating all aspects of product design, I blend strategic thinking with hands-on execution to drive business growth while advocating relentlessly for user needs.\",\n  \"experience\": [\n    {\n      \"company\": \"Future Interfaces\",\n      \"date\": \"September 2021 - Current\",\n      \"title\": \"Design Director\",\n      \"description\": \"Leading design operations for AI-powered productivity tools with a team of 15 designers\\n\u2022 Established design system reducing implementation time by 65%\\n\u2022 Pioneered accessibility-first approach resulting in WCAG AA compliance\\n\u2022 Secured $5M additional funding through successful design-led initiatives\\n\u2022 Doubled user retention through redesign of core product experiences\"\n    },\n    {\n      \"company\": \"InnovateTech Solutions\",\n      \"date\": \"April 2018 - August 2021\",\n      \"title\": \"Senior Product Designer\",\n      \"description\": \"Headed design for flagship enterprise collaboration platform\\n\u2022 Reimagined onboarding flow increasing activation rates by 47%\\n\u2022 Conducted extensive user research across 5 countries and 200+ participants\\n\u2022 Developed UX strategy aligned with business KPIs, contributing to 128% revenue growth\\n\u2022 Mentored junior designers and established design critique processes\"\n    },\n    {\n      \"company\": \"Craft Digital Agency\",\n      \"date\": \"March 2015 - March 2018\",\n      \"title\": \"UX Designer\",\n      \"description\": \"Led design for high-profile client projects across fintech, healthcare and education sectors\\n\u2022 Designed award-winning mobile banking application (UXDA Financial Design Award 2017)\\n\u2022 Created user research frameworks adopted company-wide\\n\u2022 Managed client relationships and presentation of design concepts to C-level stakeholders\"\n    }\n  ]\n}",
    "remarks":"unconventional format with complex structure"
  },
  {
    "agent_name":"resume_agent",
    "task":"extract_content",
    "id":4,
    "input":"Dr. Sarah Johnson, Ph.D.\nComputational Neuroscientist\n\nContact: sarah.johnson@neurosci.edu\nGitHub Repository: github.com\/sarahjohnson-neuro\nLinkedIn Profile: linkedin.com\/in\/sarahjohnson-neuroscience\n\nRESEARCH FOCUS\n--------------\nDeveloping computational models of neural information processing with applications in machine learning and artificial intelligence. Expert in neural networks, Bayesian modeling, and signal processing techniques for EEG\/fMRI data.\n\nACADEMIC APPOINTMENTS\n--------------------\n\nHarvard University | July 2022 - Present\nAssistant Professor, Department of Neuroscience\n- Leading the Computational Neural Dynamics Laboratory with 8 graduate students and 3 postdocs\n- Principal Investigator on NSF-funded project \"Neural Computation Models for Adaptive Learning\" ($1.8M)\n- Teaching graduate courses in Computational Neuroscience and Advanced Neural Networks\n- Published 7 papers in top-tier journals including Nature Neuroscience and PNAS\n\nMIT Brain and Cognitive Sciences | January 2019 - June 2022\nPostdoctoral Researcher\n- Developed novel algorithms for decoding neural representations from high-dimensional brain data\n- Collaborated with industry partners on brain-computer interface applications\n- Mentored 5 undergraduate research assistants and co-supervised 2 graduate students\n- Recipient of the Presidential Early Career Award for Scientists and Engineers\n\nStanford University | September 2016 - December 2018\nResearch Associate, Neural Computation Lab\n- Conducted research on statistical methods for analyzing large-scale neural recordings\n- Contributed to open-source software for neuroscience data analysis (NeuroPy)\n- Assisted in grant proposal writing, securing $750K in research funding",
    "output":"{\n  \"name\": \"Dr. Sarah Johnson, Ph.D.\",\n  \"title\": \"Computational Neuroscientist\",\n  \"email\": \"sarah.johnson@neurosci.edu\",\n  \"github\": \"github.com\/sarahjohnson-neuro\",\n  \"linkedin\": \"linkedin.com\/in\/sarahjohnson-neuroscience\",\n  \"summary\": \"Developing computational models of neural information processing with applications in machine learning and artificial intelligence. Expert in neural networks, Bayesian modeling, and signal processing techniques for EEG\/fMRI data.\",\n  \"experience\": [\n    {\n      \"company\": \"Harvard University\",\n      \"date\": \"July 2022 - Present\",\n      \"title\": \"Assistant Professor, Department of Neuroscience\",\n      \"description\": \"\u2022 Leading the Computational Neural Dynamics Laboratory with 8 graduate students and 3 postdocs\\n\u2022 Principal Investigator on NSF-funded project \\\"Neural Computation Models for Adaptive Learning\\\" ($1.8M)\\n\u2022 Teaching graduate courses in Computational Neuroscience and Advanced Neural Networks\\n\u2022 Published 7 papers in top-tier journals including Nature Neuroscience and PNAS\"\n    },\n    {\n      \"company\": \"MIT Brain and Cognitive Sciences\",\n      \"date\": \"January 2019 - June 2022\",\n      \"title\": \"Postdoctoral Researcher\",\n      \"description\": \"\u2022 Developed novel algorithms for decoding neural representations from high-dimensional brain data\\n\u2022 Collaborated with industry partners on brain-computer interface applications\\n\u2022 Mentored 5 undergraduate research assistants and co-supervised 2 graduate students\\n\u2022 Recipient of the Presidential Early Career Award for Scientists and Engineers\"\n    },\n    {\n      \"company\": \"Stanford University\",\n      \"date\": \"September 2016 - December 2018\",\n      \"title\": \"Research Associate, Neural Computation Lab\",\n      \"description\": \"\u2022 Conducted research on statistical methods for analyzing large-scale neural recordings\\n\u2022 Contributed to open-source software for neuroscience data analysis (NeuroPy)\\n\u2022 Assisted in grant proposal writing, securing $750K in research funding\"\n    }\n  ]\n}",
    "remarks":"academic cv format"
  },
  {
    "agent_name":"resume_agent",
    "task":"extract_content",
    "id":5,
    "input":"MICHAEL RODRIGUEZ\nContent Creator & Digital Marketing Specialist\n\nmike@digitalcreator.me\nlinkedin.com\/in\/michaelrodriguez-digital\ngithub.com\/mikerodz\n\n=============================\nWHO I AM\n=============================\nDigital storyteller leveraging 7+ years of experience across multiple platforms to create engaging content that converts. Self-taught programmer turned marketer with a passion for data-driven strategies and authentic brand narratives.\n\n=============================\nMY JOURNEY\n=============================\n\nFREELANCE DIGITAL CONSULTANT\nJan 2023 - Now\n\nWorking with select clients across tech, wellness, and education sectors to optimize their digital presence and content strategy.\n\nKey accomplishments:\n- Increased organic traffic by 215% for wellness startup through content optimization and SEO strategy\n- Developed and implemented social media campaigns resulting in 3x engagement rates\n- Created custom analytics dashboards for clients using Python and Google Data Studio\n- Produced video content achieving over 2M combined views across platforms\n\nGROWTHLAB MARKETING\nGrowth Hacker & Content Strategist\nMar 2021 - Dec 2022\n\n- Spearheaded content initiatives resulting in 40% increase in qualified leads\n- Managed editorial calendar and content production for blog generating 500K monthly views\n- Implemented A\/B testing protocols for landing pages improving conversion by 35%\n- Collaborated with product team to align content strategy with user acquisition goals\n\nTECHSTART MEDIA\nSocial Media Specialist\nMay 2019 - Feb 2021\n\n- Managed social presence across 5 platforms for B2B SaaS company\n- Created weekly video content series growing channel from 0 to 50K subscribers\n- Coordinated influencer partnerships resulting in 25% increase in brand mentions\n- Analyzed performance metrics to optimize content distribution strategy\n\nEARLY CAREER\n2016-2019: Various roles including Barista at CoffeeCraft while building digital skills through online courses and personal projects",
    "output":"{\n  \"name\": \"Michael Rodriguez\",\n  \"title\": \"Content Creator & Digital Marketing Specialist\",\n  \"email\": \"mike@digitalcreator.me\",\n  \"github\": \"github.com\/mikerodz\",\n  \"linkedin\": \"linkedin.com\/in\/michaelrodriguez-digital\",\n  \"summary\": \"Digital storyteller leveraging 7+ years of experience across multiple platforms to create engaging content that converts. Self-taught programmer turned marketer with a passion for data-driven strategies and authentic brand narratives.\",\n  \"experience\": [\n    {\n      \"company\": \"Freelance Digital Consultant\",\n      \"date\": \"Jan 2023 - Now\",\n      \"title\": \"Freelance Digital Consultant\",\n      \"description\": \"Working with select clients across tech, wellness, and education sectors to optimize their digital presence and content strategy.\\n\\nKey accomplishments:\\n- Increased organic traffic by 215% for wellness startup through content optimization and SEO strategy\\n- Developed and implemented social media campaigns resulting in 3x engagement rates\\n- Created custom analytics dashboards for clients using Python and Google Data Studio\\n- Produced video content achieving over 2M combined views across platforms\"\n    },\n    {\n      \"company\": \"GrowthLab Marketing\",\n      \"date\": \"Mar 2021 - Dec 2022\",\n      \"title\": \"Growth Hacker & Content Strategist\",\n      \"description\": \"- Spearheaded content initiatives resulting in 40% increase in qualified leads\\n- Managed editorial calendar and content production for blog generating 500K monthly views\\n- Implemented A\/B testing protocols for landing pages improving conversion by 35%\\n- Collaborated with product team to align content strategy with user acquisition goals\"\n    },\n    {\n      \"company\": \"TechStart Media\",\n      \"date\": \"May 2019 - Feb 2021\",\n      \"title\": \"Social Media Specialist\",\n      \"description\": \"- Managed social presence across 5 platforms for B2B SaaS company\\n- Created weekly video content series growing channel from 0 to 50K subscribers\\n- Coordinated influencer partnerships resulting in 25% increase in brand mentions\\n- Analyzed performance metrics to optimize content distribution strategy\"\n    },\n    {\n      \"company\": \"Various\",\n      \"date\": \"2016-2019\",\n      \"title\": \"Various roles\",\n      \"description\": \"Various roles including Barista at CoffeeCraft while building digital skills through online courses and personal projects\"\n    }\n  ]\n}",
    "remarks":"non-traditional format with ambiguous structure"
  },
  {
    "agent_name":"resume_agent",
    "task":"extract_content",
    "id":6,
    "input":"Luisa Fern\u00e1ndez\nArquitecta de Software & Ingeniera DevOps\n\n\ud83d\udce7 luisa.fernandez@tecnologia.es\n\ud83d\udd17 linkedin.com\/in\/luisafernandez-tech\n\ud83d\udc19 github.com\/luisaf-dev\n\nPERFIL PROFESIONAL\n------------------\nArquitecta de software con m\u00e1s de 9 a\u00f1os de experiencia en el dise\u00f1o e implementaci\u00f3n de soluciones escalables en la nube. Especializada en infraestructura como c\u00f3digo, microservicios y pr\u00e1cticas DevOps. Comunicadora efectiva capaz de liderar equipos multidisciplinarios y facilitar la adopci\u00f3n de nuevas tecnolog\u00edas.\n\nEXPERIENCIA LABORAL\n------------------\n\nGlobalTech Espa\u00f1a | Abril 2022 - Actualidad\nArquitecta de Soluciones Cloud\n- Dise\u00f1\u00e9 e implement\u00e9 arquitectura de microservicios reduciendo costos de infraestructura en un 45%\n- Lider\u00e9 la migraci\u00f3n a Kubernetes de aplicaciones legacy sin interrupciones de servicio\n- Establec\u00ed pipeline de CI\/CD aumentando frecuencia de despliegues de 2 mensuales a 20 semanales\n- Implement\u00e9 estrategias de observabilidad mejorando MTTR en un 70%\n\nNubeSoft | Enero 2019 - Marzo 2022\nDevOps Senior\n- Automatic\u00e9 procesos de infraestructura usando Terraform y Ansible\n- Dise\u00f1\u00e9 estrategia de recuperaci\u00f3n ante desastres cumpliendo RPO de 15 minutos\n- Implement\u00e9 monitoreo proactivo reduciendo incidentes en producci\u00f3n en un 60%\n- Capacit\u00e9 al equipo de desarrollo en pr\u00e1cticas de infraestructura como c\u00f3digo\n\nDesarrollos Tecnol\u00f3gicos, S.L. | Marzo 2016 - Diciembre 2018\nIngeniera de Software\n- Desarroll\u00e9 servicios backend en Java y Python para plataforma de e-commerce\n- Implement\u00e9 sistema de cach\u00e9s distribuidas mejorando latencia en un 80%\n- Colabor\u00e9 en refactorizaci\u00f3n de c\u00f3digo legacy mejorando mantenibilidad\n- Particip\u00e9 en guardias rotativas para soporte 24\/7",
    "output":"{\n  \"name\": \"Luisa Fern\u00e1ndez\",\n  \"title\": \"Arquitecta de Software & Ingeniera DevOps\",\n  \"email\": \"luisa.fernandez@tecnologia.es\",\n  \"github\": \"github.com\/luisaf-dev\",\n  \"linkedin\": \"linkedin.com\/in\/luisafernandez-tech\",\n  \"summary\": \"Arquitecta de software con m\u00e1s de 9 a\u00f1os de experiencia en el dise\u00f1o e implementaci\u00f3n de soluciones escalables en la nube. Especializada en infraestructura como c\u00f3digo, microservicios y pr\u00e1cticas DevOps. Comunicadora efectiva capaz de liderar equipos multidisciplinarios y facilitar la adopci\u00f3n de nuevas tecnolog\u00edas.\",\n  \"experience\": [\n    {\n      \"company\": \"GlobalTech Espa\u00f1a\",\n      \"date\": \"Abril 2022 - Actualidad\",\n      \"title\": \"Arquitecta de Soluciones Cloud\",\n      \"description\": \"\u2022 Dise\u00f1\u00e9 e implement\u00e9 arquitectura de microservicios reduciendo costos de infraestructura en un 45%\\n\u2022 Lider\u00e9 la migraci\u00f3n a Kubernetes de aplicaciones legacy sin interrupciones de servicio\\n\u2022 Establec\u00ed pipeline de CI\/CD aumentando frecuencia de despliegues de 2 mensuales a 20 semanales\\n\u2022 Implement\u00e9 estrategias de observabilidad mejorando MTTR en un 70%\"\n    },\n    {\n      \"company\": \"NubeSoft\",\n      \"date\": \"Enero 2019 - Marzo 2022\",\n      \"title\": \"DevOps Senior\",\n      \"description\": \"\u2022 Automatic\u00e9 procesos de infraestructura usando Terraform y Ansible\\n\u2022 Dise\u00f1\u00e9 estrategia de recuperaci\u00f3n ante desastres cumpliendo RPO de 15 minutos\\n\u2022 Implement\u00e9 monitoreo proactivo reduciendo incidentes en producci\u00f3n en un 60%\\n\u2022 Capacit\u00e9 al equipo de desarrollo en pr\u00e1cticas de infraestructura como c\u00f3digo\"\n    },\n    {\n      \"company\": \"Desarrollos Tecnol\u00f3gicos, S.L.\",\n      \"date\": \"Marzo 2016 - Diciembre 2018\",\n      \"title\": \"Ingeniera de Software\",\n      \"description\": \"\u2022 Desarroll\u00e9 servicios backend en Java y Python para plataforma de e-commerce\\n\u2022 Implement\u00e9 sistema de cach\u00e9s distribuidas mejorando latencia en un 80%\\n\u2022 Colabor\u00e9 en refactorizaci\u00f3n de c\u00f3digo legacy mejorando mantenibilidad\\n\u2022 Particip\u00e9 en guardias rotativas para soporte 24\/7\"\n    }\n  ]\n}",
    "remarks":"international format with special characters"
  },
  {
    "agent_name":"resume_agent",
    "task":"extract_content",
    "id":7,
    "input":"Robert Taylor\nFront-End Developer\n\nrob.taylor@mail.com\n\nSummary:\nFast-learning front-end developer with eye for design and focus on user experience.\n\nWork:\n\nAmazon (2023-present)\nUI Developer\n- Built new checkout experience\n- Improved page load times\n\nFreelance (2020-2023)\nWeb Developer\n- Created websites for small businesses\n- Managed client relationships",
    "output":"{\n  \"name\": \"Robert Taylor\",\n  \"title\": \"Front-End Developer\",\n  \"email\": \"rob.taylor@mail.com\",\n  \"github\": null,\n  \"linkedin\": null,\n  \"summary\": \"Fast-learning front-end developer with eye for design and focus on user experience.\",\n  \"experience\": [\n    {\n      \"company\": \"Amazon\",\n      \"date\": \"2023-present\",\n      \"title\": \"UI Developer\",\n      \"description\": \"- Built new checkout experience\\n- Improved page load times\"\n    },\n    {\n      \"company\": \"Freelance\",\n      \"date\": \"2020-2023\",\n      \"title\": \"Web Developer\",\n      \"description\": \"- Created websites for small businesses\\n- Managed client relationships\"\n    }\n  ]\n}",
    "remarks":"minimal resume with incomplete information"
  },
  {
    "agent_name":"resume_agent",
    "task":"extract_content",
    "id":8,
    "input":"=====================================================================\nNAME: Priya Patel | ROLE: MARKETING EXECUTIVE | priya.p@marketingstrategy.co\n=====================================================================\nABOUT: Strategic marketing professional with expertise in digital campaigns, \nbrand development, and market analysis. Proven record of increasing engagement \nand ROI through data-driven approaches and creative storytelling.\n=====================================================================\nFIND ME: github.com\/priyapatel-marketing | linkedin.com\/in\/priyapmarketingpro\n=====================================================================\n\nPROFESSIONAL TIMELINE\n--------------------\n\n>> CURRENT POSITION <<\nGlobal Marketing Director @ Nexus Brands International\nFrom: June 2022\n- Overseeing marketing strategies across 12 international markets\n- Directing team of 15 marketing professionals across 4 regional offices\n- Implemented rebranding initiative increasing brand recognition by 45%\n- Optimized marketing budget allocation resulting in 28% higher ROI\n\n>> PREVIOUS ROLES <<\n\nBrand Strategy Manager @ ConsumerGoods Co.\nSept 2019 - May 2022\n- Led development of brand strategies for consumer product portfolio\n- Executed omnichannel campaigns increasing engagement by 63%\n- Conducted market research identifying key growth opportunities\n- Managed relationships with external creative and media agencies\n\nDigital Marketing Specialist @ MarketingAgency Pro\nMarch 2017 - August 2019\n- Managed social media presence for Fortune 500 clients\n- Developed content calendars and campaign strategies\n- Analyzed performance metrics to optimize digital campaigns\n- Coordinated with design team to create compelling visual assets",
    "output":"{\n  \"name\": \"Priya Patel\",\n  \"title\": \"Marketing Executive\",\n  \"email\": \"priya.p@marketingstrategy.co\",\n  \"github\": \"github.com\/priyapatel-marketing\",\n  \"linkedin\": \"linkedin.com\/in\/priyapmarketingpro\",\n  \"summary\": \"Strategic marketing professional with expertise in digital campaigns, brand development, and market analysis. Proven record of increasing engagement and ROI through data-driven approaches and creative storytelling.\",\n  \"experience\": [\n    {\n      \"company\": \"Nexus Brands International\",\n      \"date\": \"June 2022\",\n      \"title\": \"Global Marketing Director\",\n      \"description\": \"\u2022 Overseeing marketing strategies across 12 international markets\\n\u2022 Directing team of 15 marketing professionals across 4 regional offices\\n\u2022 Implemented rebranding initiative increasing brand recognition by 45%\\n\u2022 Optimized marketing budget allocation resulting in 28% higher ROI\"\n    },\n    {\n      \"company\": \"ConsumerGoods Co.\",\n      \"date\": \"Sept 2019 - May 2022\",\n      \"title\": \"Brand Strategy Manager\",\n      \"description\": \"\u2022 Led development of brand strategies for consumer product portfolio\\n\u2022 Executed omnichannel campaigns increasing engagement by 63%\\n\u2022 Conducted market research identifying key growth opportunities\\n\u2022 Managed relationships with external creative and media agencies\"\n    },\n    {\n      \"company\": \"MarketingAgency Pro\",\n      \"date\": \"March 2017 - August 2019\",\n      \"title\": \"Digital Marketing Specialist\",\n      \"description\": \"\u2022 Managed social media presence for Fortune 500 clients\\n\u2022 Developed content calendars and campaign strategies\\n\u2022 Analyzed performance metrics to optimize digital campaigns\\n\u2022 Coordinated with design team to create compelling visual assets\"\n    }\n  ]\n}",
    "remarks":"hard to parse format with unusual layout"
  },
  {
    "agent_name":"resume_agent",
    "task":"extract_content",
    "id":9,
    "input":"\u25c6\u25c6\u25c6\u25c6\u25c6\u25c6\u25c6\u25c6\u25c6\u25c6\u25c6\u25c6\u25c6\u25c6\u25c6\u25c6\u25c6\u25c6\u25c6\u25c6\u25c6\u25c6\u25c6\u25c6\u25c6\u25c6\u25c6\u25c6\u25c6\u25c6\u25c6\u25c6\u25c6\u25c6\u25c6\u25c6\u25c6\u25c6\u25c6\u25c6\u25c6\u25c6\u25c6\u25c6\u25c6\u25c6\u25c6\n       OLIVIA MARTINEZ - ENVIRONMENTAL SCIENTIST\n\u25c6\u25c6\u25c6\u25c6\u25c6\u25c6\u25c6\u25c6\u25c6\u25c6\u25c6\u25c6\u25c6\u25c6\u25c6\u25c6\u25c6\u25c6\u25c6\u25c6\u25c6\u25c6\u25c6\u25c6\u25c6\u25c6\u25c6\u25c6\u25c6\u25c6\u25c6\u25c6\u25c6\u25c6\u25c6\u25c6\u25c6\u25c6\u25c6\u25c6\u25c6\u25c6\u25c6\u25c6\u25c6\u25c6\u25c6\n\nO.martinez@ecosci.org \/\/ github.com\/oliviamartinez-ecosci\nhttps:\/\/www.linkedin.com\/in\/oliviamartinez-environmental\n\n>>> OVERVIEW <<<\nEnvironmental scientist with a focus on climate resilience and habitat restoration. Combines field research experience with data analysis skills to develop evidence-based conservation strategies. Passionate advocate for community-based environmental solutions and science communication.\n\n>>> CAREER TIMELINE <<<\n\n\u2666 Environmental Research Institute \u2666\nClimate Resilience Scientist | Feb 2021 \u2192 PRESENT\n- Lead researcher on coastal ecosystem adaptation to climate change\n- Developed predictive models for sea-level rise impacts, adopted by 3 state agencies\n- Secured $450K in grant funding for community-based climate resilience projects\n- Published 5 peer-reviewed papers on wetland conservation strategies\n\n\u2666 GreenFuture Consultants \u2666 \nEnvironmental Data Analyst | Nov 2018 \u2192 Jan 2021\n- Analyzed complex environmental datasets to inform conservation planning\n- Created GIS mapping tools for habitat connectivity assessment\n- Conducted environmental impact assessments for renewable energy projects\n- Collaborated with interdisciplinary teams on sustainable development initiatives\n\n\u2666 National Park Service \u2666\nConservation Intern | May 2017 \u2192 Oct 2018\n- Assisted with wildlife monitoring and habitat assessment programs\n- Collected and processed field samples for water quality analysis\n- Participated in invasive species management projects\n- Developed educational materials for visitor center displays\u25c6\u25c6\u25c6\u25c6\u25c6\u25c6\u25c6\n       OLIVIA MARTINEZ - ENVIRONMENTAL SCIENTIST\n\u25c6\u25c6\u25c6\u25c6\u25c6\u25c6\u25c6\u25c6\u25c6\u25c6\u25c6\u25c6\u25c6\u25c6\u25c6\u25c6\u25c6\u25c6\u25c6\u25c6\u25c6\u25c6\u25c6\u25c6\u25c6\u25c6\u25c6\u25c6\u25c6\u25c6\u25c6\u25c6\u25c6\u25c6\u25c6\u25c6\u25c6\u25c6\u25c6\u25c6\u25c6\u25c6\u25c6\u25c6\u25c6\u25c6\u25c6",
    "output":"{\n  \"name\": \"Olivia Martinez\",\n  \"title\": \"Environmental Scientist\",\n  \"email\": \"O.martinez@ecosci.org\",\n  \"github\": \"github.com\/oliviamartinez-ecosci\",\n  \"linkedin\": \"linkedin.com\/in\/oliviamartinez-environmental\",\n  \"summary\": \"Environmental scientist with a focus on climate resilience and habitat restoration. Combines field research experience with data analysis skills to develop evidence-based conservation strategies. Passionate advocate for community-based environmental solutions and science communication.\",\n  \"experience\": [\n    {\n      \"company\": \"Environmental Research Institute\",\n      \"date\": \"Feb 2021 \u2192 PRESENT\",\n      \"title\": \"Climate Resilience Scientist\",\n      \"description\": \"\u2022 Lead researcher on coastal ecosystem adaptation to climate change\\n\u2022 Developed predictive models for sea-level rise impacts, adopted by 3 state agencies\\n\u2022 Secured $450K in grant funding for community-based climate resilience projects\\n\u2022 Published 5 peer-reviewed papers on wetland conservation strategies\"\n    },\n    {\n      \"company\": \"GreenFuture Consultants\",\n      \"date\": \"Nov 2018 \u2192 Jan 2021\",\n      \"title\": \"Environmental Data Analyst\",\n      \"description\": \"\u2022 Analyzed complex environmental datasets to inform conservation planning\\n\u2022 Created GIS mapping tools for habitat connectivity assessment\\n\u2022 Conducted environmental impact assessments for renewable energy projects\\n\u2022 Collaborated with interdisciplinary teams on sustainable development initiatives\"\n    },\n    {\n      \"company\": \"National Park Service\",\n      \"date\": \"May 2017 \u2192 Oct 2018\",\n      \"title\": \"Conservation Intern\",\n      \"description\": \"\u2022 Assisted with wildlife monitoring and habitat assessment programs\\n\u2022 Collected and processed field samples for water quality analysis\\n\u2022 Participated in invasive species management projects\\n\u2022 Developed educational materials for visitor center displays\"\n    }\n  ]\n}",
    "remarks":"mixed format with unusual characters"
  },
  {
    "agent_name":"resume_agent",
    "task":"extract_content",
    "id":10,
    "input":"I need help creating a resume. My name is Thomas Anderson and I work as a Software Security Engineer. My email is thomas.a@securemail.net, and you can find me on GitHub at github.com\/thomas-security and LinkedIn at linkedin.com\/in\/thomas-anderson-security.\n\nI've been working in cybersecurity for about 7 years now. I'm passionate about building secure systems from the ground up and finding vulnerabilities before they can be exploited. I'm particularly interested in application security and secure coding practices.\n\nMy most recent job is at CyberDefend Technologies where I've been a Senior Security Engineer since March 2022. My main responsibilities include performing security code reviews, implementing security controls in our flagship product, and leading threat modeling sessions with the development team. I've managed to reduce our critical vulnerabilities by 85% and implemented a secure development lifecycle that's become the standard across all company projects.\n\nBefore that, I worked at SecureNet Inc. as a Security Developer from January 2019 to February 2022. There, I developed security modules for client applications, conducted penetration testing, and created automated security scanning tools that improved our assessment efficiency by 70%. I also trained junior developers on secure coding practices.\n\nMy first real job in the field was at TechGuard Solutions as a Junior Security Analyst from June 2017 to December 2018. I mainly assisted with vulnerability assessments, monitored security systems, and helped document security policies and procedures.",
    "output":"{\n  \"name\": \"Thomas Anderson\",\n  \"title\": \"Software Security Engineer\",\n  \"email\": \"thomas.a@securemail.net\",\n  \"github\": \"github.com\/thomas-security\",\n  \"linkedin\": \"linkedin.com\/in\/thomas-anderson-security\",\n  \"summary\": \"I've been working in cybersecurity for about 7 years now. I'm passionate about building secure systems from the ground up and finding vulnerabilities before they can be exploited. I'm particularly interested in application security and secure coding practices.\",\n  \"experience\": [\n    {\n      \"company\": \"CyberDefend Technologies\",\n      \"date\": \"March 2022 - Present\",\n      \"title\": \"Senior Security Engineer\",\n      \"description\": \"My main responsibilities include performing security code reviews, implementing security controls in our flagship product, and leading threat modeling sessions with the development team. I've managed to reduce our critical vulnerabilities by 85% and implemented a secure development lifecycle that's become the standard across all company projects.\"\n    },\n    {\n      \"company\": \"SecureNet Inc.\",\n      \"date\": \"January 2019 - February 2022\",\n      \"title\": \"Security Developer\",\n      \"description\": \"There, I developed security modules for client applications, conducted penetration testing, and created automated security scanning tools that improved our assessment efficiency by 70%. I also trained junior developers on secure coding practices.\"\n    },\n    {\n      \"company\": \"TechGuard Solutions\",\n      \"date\": \"June 2017 - December 2018\",\n      \"title\": \"Junior Security Analyst\",\n      \"description\": \"I mainly assisted with vulnerability assessments, monitored security systems, and helped document security policies and procedures.\"\n    }\n  ]\n}",
    "remarks":"complete information in conversational"
  },
  {
    "agent_name":"resume_agent",
    "task":"extract_content",
    "id":11,
    "input":"I want to create a resume. My name is Jessica Wong and I'm a graphic designer. Here's what I've been doing:\n\nCurrently I'm working as a Senior Designer at Creative Minds Studio since 2021. I lead branding projects for major clients, manage a team of junior designers, and have won several industry awards for my work. One of my recent campaigns increased client engagement by 45%.\n\nBefore that, I was at DesignHub from 2018 to 2021 as a Graphic Designer where I created visual identities for various clients and collaborated with the marketing team on campaign materials. I also redesigned the company's website, which resulted in a 30% increase in inquiries.\n\nMy first job was as a Design Intern at ArtWorks Agency for about 8 months in 2017-2018. I mainly assisted senior designers and learned about the professional design workflow.\n\nYou can check out some of my work on my LinkedIn: linkedin.com\/in\/jessicawongdesign",
    "output":"{\n  \"name\": \"Jessica Wong\",\n  \"title\": \"Graphic Designer\",\n  \"email\": null,\n  \"github\": null,\n  \"linkedin\": \"linkedin.com\/in\/jessicawongdesign\",\n  \"summary\": null,\n  \"experience\": [\n    {\n      \"company\": \"Creative Minds Studio\",\n      \"date\": \"2021 - Present\",\n      \"title\": \"Senior Designer\",\n      \"description\": \"I lead branding projects for major clients, manage a team of junior designers, and have won several industry awards for my work. One of my recent campaigns increased client engagement by 45%.\"\n    },\n    {\n      \"company\": \"DesignHub\",\n      \"date\": \"2018 - 2021\",\n      \"title\": \"Graphic Designer\",\n      \"description\": \"I created visual identities for various clients and collaborated with the marketing team on campaign materials. I also redesigned the company's website, which resulted in a 30% increase in inquiries.\"\n    },\n    {\n      \"company\": \"ArtWorks Agency\",\n      \"date\": \"2017 - 2018\",\n      \"title\": \"Design Intern\",\n      \"description\": \"I mainly assisted senior designers and learned about the professional design workflow.\"\n    }\n  ]\n}",
    "remarks":"incomplete information with missing fields"
  },
  {
    "agent_name":"resume_agent",
    "task":"extract_content",
    "id":12,
    "input":"My name is Miguel Rodriguez and I'm looking to create a resume for my job search. I've been working as a Marketing Manager at Procter & Gamble for about 4 years now. Before that, I was a Marketing Specialist at Johnson & Johnson from 2017 to 2020.\n\nAt P&G, I've managed campaigns for several major product launches and increased social media engagement by 78%. I also led a team of 3 content creators and coordinated with our sales department on promotional strategies.\n\nI'm good at digital marketing, brand strategy, and team leadership. Could you help me format this into a proper resume? Oh, and my email is miguel.r@email.com.",
    "output":"{\n  \"name\": \"Miguel Rodriguez\",\n  \"title\": \"Marketing Manager\",\n  \"email\": \"miguel.r@email.com\",\n  \"github\": null,\n  \"linkedin\": null,\n  \"summary\": \"Skilled in digital marketing, brand strategy, and team leadership.\",\n  \"experience\": [\n    {\n      \"company\": \"Procter & Gamble\",\n      \"date\": \"2020 - Present\",\n      \"title\": \"Marketing Manager\",\n      \"description\": \"Managed campaigns for several major product launches and increased social media engagement by 78%. Led a team of 3 content creators and coordinated with the sales department on promotional strategies.\"\n    },\n    {\n      \"company\": \"Johnson & Johnson\",\n      \"date\": \"2017 - 2020\",\n      \"title\": \"Marketing Specialist\",\n      \"description\": null\n    }\n  ]\n}",
    "remarks":"partial information with missing fields"
  },
  {
    "agent_name":"resume_agent",
    "task":"extract_content",
    "id":13,
    "input":"Hi there! I need help organizing my professional experience for a resume. I'm Jennifer Wilson (jen.wilson@email.com) and I've been working in the finance industry for about 8 years.\n\nI started at Bank of America as a Financial Analyst (I think it was around May 2015) and stayed until early 2018. Then I moved to JP Morgan Chase as a Senior Financial Analyst until December 2020. Now I'm at Goldman Sachs as a Vice President of Financial Planning since January 2021.\n\nMy responsibilities at Goldman include overseeing the annual budgeting process, developing financial models for business projections, and presenting quarterly performance reports to executives. At JP Morgan, I was responsible for analyzing investment opportunities and creating detailed financial reports.\n\nYou can check out my LinkedIn at linkedin.com\/in\/jenniferwilson if you need more info. I'm skilled in financial modeling, budget management, and strategic planning. Thanks for helping me put this together!",
    "output":"{\n  \"name\": \"Jennifer Wilson\",\n  \"title\": \"Vice President of Financial Planning\",\n  \"email\": \"jen.wilson@email.com\",\n  \"github\": null,\n  \"linkedin\": \"linkedin.com\/in\/jenniferwilson\",\n  \"summary\": \"Skilled in financial modeling, budget management, and strategic planning with 8 years of experience in the finance industry.\",\n  \"experience\": [\n    {\n      \"company\": \"Goldman Sachs\",\n      \"date\": \"January 2021 - Present\",\n      \"title\": \"Vice President of Financial Planning\",\n      \"description\": \"Overseeing the annual budgeting process, developing financial models for business projections, and presenting quarterly performance reports to executives.\"\n    },\n    {\n      \"company\": \"JP Morgan Chase\",\n      \"date\": \"Early 2018 - December 2020\",\n      \"title\": \"Senior Financial Analyst\",\n      \"description\": \"Responsible for analyzing investment opportunities and creating detailed financial reports.\"\n    },\n    {\n      \"company\": \"Bank of America\",\n      \"date\": \"May 2015 - Early 2018\",\n      \"title\": \"Financial Analyst\",\n      \"description\": null\n    }\n  ]\n}",
    "remarks":"messy format with ambiguous information"
  },
  {
    "agent_name":"resume_agent",
    "task":"extract_content",
    "id":14,
    "input":"I've been working on updating my professional profile. I'm David Park, and I've spent the last decade in the healthcare technology sector.\n\nI started my journey at Epic Systems, where I worked as a Healthcare Systems Analyst from 2013 to 2017. My main focus was implementing electronic health record systems for large hospital networks and training staff on new software solutions.\n\nIn 2017, I joined Cerner Corporation as a Project Manager, where I led cross-functional teams in deploying integrated healthcare IT solutions. One of my key achievements was completing a major hospital system integration three weeks ahead of schedule and under budget.\n\nSince March 2021, I've been serving as the Director of Health Informatics at Kaiser Permanente. My team focuses on leveraging data analytics to improve patient outcomes and streamline clinical workflows. We recently developed a predictive model that helped reduce readmission rates by 23%.\n\nI hold a Master's degree in Health Informatics from Johns Hopkins University and am certified in Project Management (PMP). I'm passionate about using technology to improve healthcare delivery and patient experiences.\n\nIf you need to reach me, my email is david.park@email.com. My GitHub username is dpark-health, and you can find me on LinkedIn at linkedin.com\/in\/davidpark-health.",
    "output":"{\n  \"name\": \"David Park\",\n  \"title\": \"Director of Health Informatics\",\n  \"email\": \"david.park@email.com\",\n  \"github\": \"github.com\/dpark-health\",\n  \"linkedin\": \"linkedin.com\/in\/davidpark-health\",\n  \"summary\": \"Experienced healthcare technology professional with a decade in the sector. Holds a Master's degree in Health Informatics from Johns Hopkins University and is certified in Project Management (PMP). Passionate about using technology to improve healthcare delivery and patient experiences.\",\n  \"experience\": [\n    {\n      \"company\": \"Kaiser Permanente\",\n      \"date\": \"March 2021 - Present\",\n      \"title\": \"Director of Health Informatics\",\n      \"description\": \"Leads a team focusing on leveraging data analytics to improve patient outcomes and streamline clinical workflows. Recently developed a predictive model that helped reduce readmission rates by 23%.\"\n    },\n    {\n      \"company\": \"Cerner Corporation\",\n      \"date\": \"2017 - March 2021\",\n      \"title\": \"Project Manager\",\n      \"description\": \"Led cross-functional teams in deploying integrated healthcare IT solutions. Completed a major hospital system integration three weeks ahead of schedule and under budget.\"\n    },\n    {\n      \"company\": \"Epic Systems\",\n      \"date\": \"2013 - 2017\",\n      \"title\": \"Healthcare Systems Analyst\",\n      \"description\": \"Implemented electronic health record systems for large hospital networks and trained staff on new software solutions.\"\n    }\n  ]\n}",
    "remarks":"multi paragraph text with implicit information"
  },
  {
    "agent_name":"resume_agent",
    "task":"extract_content",
    "id":15,
    "input":"ALEX JOHNSON\nSenior Software Engineer\n\nalexjohnson@email.com | github.com\/alexjohnson | linkedin.com\/in\/alexjohnson\n(555) 123-4567 | San Francisco, CA\n\nSUMMARY\nExperienced software engineer with 7+ years of experience building scalable web applications and leading development teams. Expertise in JavaScript, Python, and cloud architecture.\n\nEXPERIENCE\n\nGoogle, Inc.\nSenior Software Engineer\nJanuary 2021 - Present\n- Led a team of 5 engineers to redesign the customer-facing dashboard, improving user engagement by 35%\n- Architected and implemented a serverless microservice solution that reduced infrastructure costs by 40%\n- Mentored junior developers and conducted technical interviews for new hires\n\nSalesforce\nSoftware Engineer\nMarch 2018 - December 2020\n- Developed RESTful APIs consumed by frontend applications with over 10,000 daily active users\n- Implemented automated testing suite that improved code coverage from 65% to 92%\n- Collaborated with product managers to define requirements and technical specifications\n\nEDUCATION\nStanford University - Master of Science, Computer Science\nUniversity of California, Berkeley - Bachelor of Science, Computer Science",
    "output":"{\n  \"name\": \"Alex Johnson\",\n  \"title\": \"Senior Software Engineer\",\n  \"email\": \"alexjohnson@email.com\",\n  \"github\": \"github.com\/alexjohnson\",\n  \"linkedin\": \"linkedin.com\/in\/alexjohnson\",\n  \"summary\": \"Experienced software engineer with 7+ years of experience building scalable web applications and leading development teams. Expertise in JavaScript, Python, and cloud architecture.\",\n  \"experience\": [\n    {\n      \"company\": \"Google, Inc.\",\n      \"date\": \"January 2021 - Present\",\n      \"title\": \"Senior Software Engineer\",\n      \"description\": \"- Led a team of 5 engineers to redesign the customer-facing dashboard, improving user engagement by 35%\\n- Architected and implemented a serverless microservice solution that reduced infrastructure costs by 40%\\n- Mentored junior developers and conducted technical interviews for new hires\"\n    },\n    {\n      \"company\": \"Salesforce\",\n      \"date\": \"March 2018 - December 2020\",\n      \"title\": \"Software Engineer\",\n      \"description\": \"- Developed RESTful APIs consumed by frontend applications with over 10,000 daily active users\\n- Implemented automated testing suite that improved code coverage from 65% to 92%\\n- Collaborated with product managers to define requirements and technical specifications\"\n    }\n  ]\n}",
    "remarks":"well-structured with complete information"
  }
]
